MANIFEST.in
README.rst
VERSION
conftest.py
requirements.txt
setup.cfg
setup.py
PyKyu.egg-info/PKG-INFO
PyKyu.egg-info/SOURCES.txt
PyKyu.egg-info/dependency_links.txt
PyKyu.egg-info/top_level.txt
docs/Makefile
docs/conf.py
docs/development.rst
docs/example.inc.rst
docs/index.rst
pykyu/__init__.py
tests/test_default.py
tests/test_package.py