Metadata-Version: 1.1
Name: PyKyu
Version: 1.0
Summary: Process queueing; declarative, configurable.
Home-page: https://bitbucket.org/creeerio/pykyu
Author: Nils
Author-email: nils@creeer.io
License: MIT
Platform: UNKNOWN
Classifier: Development Status :: 3 - Alpha
Classifier: Intended Audience :: Developers
Classifier: License :: OSI Approved :: MIT License
Classifier: Programming Language :: Python :: 3.5
